dropbox_api_team_5.py
dropbox_api_team_5-0.1.0.dist-info/WHEEL
dropbox_api_team_5-0.1.0.dist-info/METADATA
dropbox_api_team_5-0.1.0.dist-info/RECORD
